JointCloudStorage/__init__.py
JointCloudStorage/auth.py
JointCloudStorage/bucket.py
JointCloudStorage/exceptions.py
JointCloudStorage/state.py
jcs_sdk-1.7.25.dist-info/METADATA
jcs_sdk-1.7.25.dist-info/WHEEL
jcs_sdk-1.7.25.dist-info/top_level.txt
jcs_sdk-1.7.25.dist-info/RECORD
