Metadata-Version: 2.1
Name: jcs-sdk
Version: 1.7.25
Summary: This is the official Python SDK for JointCloudStorage
Home-page: https://www.jointcloudstorage.cn
Author: sincerexia
Author-email: zhangjh@act.buaa.edu.cn
License: UNKNOWN
Platform: UNKNOWN
Requires-Python: >=3.6
Requires-Dist: requests (>=2.26.0)
